README.rst
setup.cfg
setup.py
deterministic_encryption_utils/__init__.py
deterministic_encryption_utils.egg-info/PKG-INFO
deterministic_encryption_utils.egg-info/SOURCES.txt
deterministic_encryption_utils.egg-info/dependency_links.txt
deterministic_encryption_utils.egg-info/requires.txt
deterministic_encryption_utils.egg-info/top_level.txt
deterministic_encryption_utils/encryption/Encryption.py
deterministic_encryption_utils/encryption/EncryptionExtensions.py
deterministic_encryption_utils/encryption/Padding.py
deterministic_encryption_utils/encryption/VirtualFile.py
deterministic_encryption_utils/encryption/__init__.py
deterministic_encryption_utils/encryption/extensions/ExtensionRegistry.py
deterministic_encryption_utils/encryption/extensions/ModificationTimeFileSaltProvider.py
deterministic_encryption_utils/encryption/extensions/ModificationTimeFilenameSaltProvider.py
deterministic_encryption_utils/encryption/extensions/NameFileSaltProvider.py
deterministic_encryption_utils/encryption/extensions/NameFilenameSaltProvider.py
deterministic_encryption_utils/encryption/extensions/__init__.py