Metadata-Version: 1.1
Name: deterministic-encryption-utils
Version: 0.3.0
Summary: Common encryption utilities for the implementation of simple encryption/decryption views.
Home-page: https://github.com/seiferma/deterministic_encryption_utils
Author: Stephan Seifermann
Author-email: seiferma@t-online.de
License: MIT
Keywords: encryption view decryption library
Platform: UNKNOWN
Classifier: Development Status :: 5 - Production/Stable
Classifier: Environment :: No Input/Output (Daemon)
Classifier: Intended Audience :: Developers
Classifier: Topic :: Software Development :: Libraries :: Python Modules
Classifier: License :: OSI Approved :: MIT License
Classifier: Operating System :: OS Independent
Classifier: Programming Language :: Python :: 3 :: Only
